xenon_lfp_analysis/__init__.py
xenon_lfp_analysis/convert_utaharray.py
xenon_lfp_analysis/downsample_brw.py
xenon_lfp_analysis/run_lfp_analysis.py
xenon_lfp_analysis/app/__init__.py
xenon_lfp_analysis/app/app.py
xenon_lfp_analysis/app/app.wsgi
xenon_lfp_analysis-0.0.4.dist-info/LICENSE
xenon_lfp_analysis-0.0.4.dist-info/METADATA
xenon_lfp_analysis-0.0.4.dist-info/WHEEL
xenon_lfp_analysis-0.0.4.dist-info/entry_points.txt
xenon_lfp_analysis-0.0.4.dist-info/top_level.txt
xenon_lfp_analysis-0.0.4.dist-info/zip-safe
xenon_lfp_analysis-0.0.4.dist-info/RECORD
