Metadata-Version: 2.1
Name: xenon-lfp-analysis
Version: 0.0.4
Summary: Xenon LFP Analysis Platform
Home-page: https://github.com/MicroBrew09/xenon-lfp-analysis.git
Author: Arjun Mahadevan
Author-email: Arjun Mahadevan <amahadevan@xenon-pharma.com>
Classifier: License :: OSI Approved :: MIT License
Requires-Python: >=3.7
License-File: LICENSE
Requires-Dist: pyaedt (==0.4.7)
Requires-Dist: Django (==3.2.8)
Requires-Dist: Brotli (==1.0.9)
Requires-Dist: click (==8.0.4)
Requires-Dist: colorama (==0.4.4)
Requires-Dist: dash (==2.2.0)
Requires-Dist: dash-core-components (==2.0.0)
Requires-Dist: dash-daq (==0.5.0)
Requires-Dist: dash-html-components (==2.0.0)
Requires-Dist: dash-table (==5.0.0)
Requires-Dist: Flask (==2.0.3)
Requires-Dist: flask-caching
Requires-Dist: Flask-Compress (==1.11)
Requires-Dist: h5py (==3.6.0)
Requires-Dist: imageio (==2.16.1)
Requires-Dist: itsdangerous (==2.1.1)
Requires-Dist: Jinja2 (==3.0.3)
Requires-Dist: MarkupSafe (==2.1.0)
Requires-Dist: networkx
Requires-Dist: numpy
Requires-Dist: packaging (==21.3)
Requires-Dist: pandas
Requires-Dist: Pillow (==9.0.1)
Requires-Dist: plotly (==5.6.0)
Requires-Dist: pyparsing (==3.0.7)
Requires-Dist: python-dateutil (==2.8.2)
Requires-Dist: pytz (==2021.3)
Requires-Dist: PyWavelets (==1.3.0)
Requires-Dist: scikit-image (==0.19.2)
Requires-Dist: scipy
Requires-Dist: six (==1.16.0)
Requires-Dist: tenacity (==8.0.1)
Requires-Dist: Werkzeug (==2.0.3)
Requires-Dist: tqdm (==2.2.3)
Requires-Dist: kaleido (==0.2.1)
Provides-Extra: all
Requires-Dist: Brotli ; extra == 'all'
Requires-Dist: click ; extra == 'all'
Requires-Dist: colorama ; extra == 'all'
Requires-Dist: dash ; extra == 'all'
Requires-Dist: dash-core-components ; extra == 'all'
Requires-Dist: dash-daq ; extra == 'all'
Requires-Dist: dash-html-components ; extra == 'all'
Requires-Dist: dash-table ; extra == 'all'
Requires-Dist: Flask ; extra == 'all'
Requires-Dist: Flask-Compress ; extra == 'all'
Requires-Dist: h5py ; extra == 'all'
Requires-Dist: imageio ; extra == 'all'
Requires-Dist: itsdangerous ; extra == 'all'
Requires-Dist: Jinja2 ; extra == 'all'
Requires-Dist: MarkupSafe ; extra == 'all'
Requires-Dist: networkx ; extra == 'all'
Requires-Dist: numpy ; extra == 'all'
Requires-Dist: packaging ; extra == 'all'
Requires-Dist: pandas ; extra == 'all'
Requires-Dist: Pillow ; extra == 'all'
Requires-Dist: plotly ; extra == 'all'
Requires-Dist: pyparsing ; extra == 'all'
Requires-Dist: python-dateutil ; extra == 'all'
Requires-Dist: pytz ; extra == 'all'
Requires-Dist: PyWavelets ; extra == 'all'
Requires-Dist: scikit-image ; extra == 'all'
Requires-Dist: scipy ; extra == 'all'
Requires-Dist: six ; extra == 'all'
Requires-Dist: tenacity ; extra == 'all'
Requires-Dist: tifffile ; extra == 'all'
Requires-Dist: Werkzeug ; extra == 'all'
Requires-Dist: tqdm ; extra == 'all'
Requires-Dist: kaleido ; extra == 'all'
